[
  {
    "news": "Pichle 24 ghante me kya hua hai, aayiye jaldi se dekhte hain badi khabrein!",
    "keywords": ["news", "headline", "update"]
  },
  {
    "news": "Delhi ki hawaaj vapas bure halaat mein hain! Diwali ke subah AQI 'bahut kharab', GRAP II ke tahat naye niyam lagu.",
    "keywords": ["Delhi", "AQI", "pollution"]
  },
  {
    "news": "INS Vikrant par Diwali manate PM Modi! Kya hai iss powerful aircraft carrier ki 10 khaas baatein?",
    "keywords": ["INS Vikrant", "PM Modi", "Navy"]
  },
  {
    "news": "Nizamabad mein drama! Ek constable ke katal ka aaropi hospital se bhagne ki koshish mein encounter mein maara gaya.",
    "keywords": ["Nizamabad", "murder", "encounter"]
  },
  {
    "news": "Australia se kis cheez ko chhupa raha hai China? Samjhiye is anmol cheez ko jo hai sabke nazron mein.",
    "keywords": ["Australia", "China", "resources"]
  },
  {
    "news": "Baarish ne bigada Chennai ka Diwali mood! CM MK Stalin ne tayariyon ka liya jaiza.",
    "keywords": ["Chennai", "rain", "Diwali"]
  },
  {
    "news": "Israel ne Gaza ko madad roki! Laga ke ceasefire ko nayi jung se mila chunauti.",
    "keywords": ["Israel", "Gaza", "ceasefire"]
  },
  {
    "news": "Bihar chunav se JMM ne kheencha haath! RJD par seat-sharing baatcheet mein chaalaaki ka aarop.",
    "keywords": ["Bihar elections", "JMM", "RJD"]
  },
  {
    "news": "Devdutt Pattanaik se jaaniye Ram ke Ayodhya waapasi ki kahani, Diwali ke halke ke kahaniyon ka ek hissa.",
    "keywords": ["Devdutt Pattanaik", "Rama", "Diwali"]
  },
  {
    "news": "Southeast BoB mein cyclonic circulation intense hone ka asar! October 23 tak depression ka roop le sakta hai.",
    "keywords": ["cyclonic", "depression", "weather"]
  },
  {
    "news": "Thiruvananthapuram mein tattoo artist ne road rage mein revolver nikaala! Police ne ki giraftar.",
    "keywords": ["Thiruvananthapuram", "tattoo artist", "road rage"]
  },
  {
    "news": "Toh, aaj ke liye itna hi. Hamari team aapko har nai khabar se update rakhti rahegi. Tab tak ke liye, apna khayal rakhen aur surakshit rahen. Namaskar.",
    "keywords": ["goodbye", "stay safe", "news update"]
  }
]